mengling_tool/__init__.py
mengling_tool/asynchronous_tool.py
mengling_tool/calendar.py
mengling_tool/data_analysis.py
mengling_tool/data_make.py
mengling_tool/data_structure.py
mengling_tool/desktop.ini
mengling_tool/file_tool.py
mengling_tool/genetic_algorithm.py
mengling_tool/json_tool.py
mengling_tool/notice_tool.py
mengling_tool/pandas_tool.py
mengling_tool/pic_tool.py
mengling_tool/play.py
mengling_tool/time_tool1.py
mengling_tool/time_tool2.py
mengling_tool/time_tool3.py
mengling_tool/view_tool.py
mengling_tool/view_tool2.py
mengling_tool/window_action.py
mengling_tool/word_tool.py
mengling_tool/__data_structure__/dynamic_cache.py
mengling_tool/__data_structure__/goods.py
mengling_tool/__data_structure__/link.py
mengling_tool/__data_structure__/ring_twoway_link.py
mengling_tool/__data_structure__/synchronize_iterate.py
mengling_tool/__data_structure__/synchronize_many.py
mengling_tool/__data_structure__/__pycache__/goods.cpython-39.pyc
mengling_tool/__data_structure__/__pycache__/synchronize_iterate.cpython-39.pyc
mengling_tool/advanced_process/api.py
mengling_tool/advanced_process/key_value.py
mengling_tool/advanced_process/__pycache__/api.cpython-39.pyc
mengling_tool/advanced_process/combine_data1/数据_增量.py
mengling_tool/advanced_process/combine_data1/组合_数据.py
mengling_tool/advanced_process/combine_data1/组合_数据_单组.py
mengling_tool/advanced_process/combine_data1/__pycache__/组合_数据.cpython-39.pyc
mengling_tool/advanced_process/combine_data1/__pycache__/组合_数据_单组.cpython-39.pyc
mengling_tool/advanced_process/combine_data1/代码模板/单组.py
mengling_tool/advanced_process/combine_data1/代码模板/多组.py
mengling_tool/advanced_process/combine_data1/代码模板/键值.py
mengling_tool/advanced_process/combine_data2/config.py
mengling_tool/advanced_process/combine_data2/data.py
mengling_tool/advanced_process/combine_data2/insert.py
mengling_tool/advanced_process/combine_data2/main.py
mengling_tool/advanced_process/combine_data2/模板.py
mengling_tool-4.1.0.dist-info/METADATA
mengling_tool-4.1.0.dist-info/WHEEL
mengling_tool-4.1.0.dist-info/top_level.txt
mengling_tool-4.1.0.dist-info/RECORD
