Metadata-Version: 2.1
Name: mengling-tool
Version: 4.1.0
Summary: 工业化! yyds
Home-page: https://www.python.org
Author: mengling
Author-email: 1321443305@qq.com
Requires-Python: >=3.6
Requires-Dist: httpx
Requires-Dist: requests
Requires-Dist: tqdm
Requires-Dist: opencv-python
Requires-Dist: numpy
Requires-Dist: pandas
Requires-Dist: pymysql
